ebsynth.py
ebsynth-0.0.2.dist-info/METADATA
ebsynth-0.0.2.dist-info/WHEEL
ebsynth-0.0.2.dist-info/top_level.txt
ebsynth-0.0.2.dist-info/RECORD
