Metadata-Version: 2.1
Name: ebsynth
Version: 0.0.2
Summary: EbSynth for Python
Author: Secret Weapons
Author-email: team@scrtwpns.com
Project-URL: homepage, https://ebsynth.com
Keywords: ebsynth
